opensection/__init__.py
opensection/eurocodes/__init__.py
opensection/eurocodes/verification.py
opensection/geometry/__init__.py
opensection/geometry/contour.py
opensection/geometry/properties.py
opensection/geometry/section.py
opensection/interaction/__init__.py
opensection/interaction/diagram.py
opensection/materials/__init__.py
opensection/materials/concrete.py
opensection/materials/steel.py
opensection/postprocess/__init__.py
opensection/postprocess/report.py
opensection/postprocess/visualization.py
opensection/reinforcement/__init__.py
opensection/reinforcement/helpers.py
opensection/reinforcement/rebar.py
opensection/solver/__init__.py
opensection/solver/api.py
opensection/solver/section_solver.py
opensection/utils/__init__.py
opensection/utils/constants.py
opensection/utils/math_helpers.py
opensection/utils/units.py
opensection/validation/__init__.py
opensection/validation/analytical_cases.py
opensection/validation/exceptions.py
opensection/validation/validators.py
opensection-1.0.0.dist-info/licenses/LICENSE
opensection-1.0.0.dist-info/METADATA
opensection-1.0.0.dist-info/WHEEL
opensection-1.0.0.dist-info/top_level.txt
opensection-1.0.0.dist-info/RECORD
