Metadata-Version: 2.4
Name: opensection
Version: 1.0.0
Summary: Professional concrete section analysis - Structural concrete design according to Eurocodes
Author-email: opensection Contributors <pavlishenku@gmail.com>
Maintainer-email: opensection Contributors <pavlishenku@gmail.com>
License: MIT
Project-URL: Homepage, https://github.com/Pavlishenku/opensection
Project-URL: Documentation, https://opensection.readthedocs.io
Project-URL: Repository, https://github.com/Pavlishenku/opensection
Project-URL: Bug Tracker, https://github.com/Pavlishenku/opensection/issues
Project-URL: Changelog, https://github.com/Pavlishenku/opensection/blob/main/CHANGELOG.md
Keywords: structural-engineering,concrete-design,eurocode,civil-engineering,finite-element,building-design,scientific-computing
Classifier: Development Status :: 5 - Production/Stable
Classifier: Intended Audience :: Science/Research
Classifier: Intended Audience :: Developers
Classifier: License :: OSI Approved :: MIT License
Classifier: Operating System :: OS Independent
Classifier: Programming Language :: Python :: 3
Classifier: Programming Language :: Python :: 3.8
Classifier: Programming Language :: Python :: 3.9
Classifier: Programming Language :: Python :: 3.10
Classifier: Programming Language :: Python :: 3.11
Classifier: Programming Language :: Python :: 3.12
Classifier: Topic :: Scientific/Engineering
Classifier: Topic :: Scientific/Engineering :: Physics
Classifier: Typing :: Typed
Requires-Python: >=3.8
License-File: LICENSE
Requires-Dist: numpy>=1.20.0
Requires-Dist: matplotlib>=3.3.0
Provides-Extra: dev
Requires-Dist: pytest>=7.0.0; extra == "dev"
Requires-Dist: pytest-cov>=3.0.0; extra == "dev"
Requires-Dist: black>=22.0.0; extra == "dev"
Requires-Dist: flake8>=4.0.0; extra == "dev"
Requires-Dist: mypy>=0.950; extra == "dev"
Requires-Dist: isort>=5.10.0; extra == "dev"
Provides-Extra: docs
Requires-Dist: sphinx>=4.5.0; extra == "docs"
Requires-Dist: sphinx-rtd-theme>=1.0.0; extra == "docs"
Requires-Dist: sphinx-intl>=2.0.0; extra == "docs"
Requires-Dist: myst-parser>=0.18.0; extra == "docs"
Provides-Extra: test
Requires-Dist: pytest>=7.0.0; extra == "test"
Requires-Dist: pytest-cov>=3.0.0; extra == "test"
Requires-Dist: hypothesis>=6.0.0; extra == "test"
Dynamic: license-file
